bevy/events/__init__.py
bevy/events/dispatch.py
bevy/events/event.py
bevy.events-0.1.4.dist-info/LICENSE
bevy.events-0.1.4.dist-info/WHEEL
bevy.events-0.1.4.dist-info/METADATA
bevy.events-0.1.4.dist-info/RECORD
