Metadata-Version: 2.1
Name: bevy.events
Version: 0.1.4
Summary: An event dispatch framework designed to be used with the Bevy dependency injection framework.
Home-page: https://github.com/ZechCodes/Bevy/tree/main/bevy/events
License: MIT
Keywords: dependency,injection,annotations,types
Author: Zech Zimmerman
Author-email: hi@zech.codes
Requires-Python: >=3.7,<4.0
Classifier: Development Status :: 4 - Beta
Classifier: License :: OSI Approved :: MIT License
Classifier: Programming Language :: Python :: 3
Classifier: Programming Language :: Python :: 3.7
Classifier: Programming Language :: Python :: 3.8
Classifier: Programming Language :: Python :: 3.9
Classifier: Topic :: Software Development :: Libraries :: Application Frameworks
Requires-Dist: gully (>=0.3,<0.4)
Project-URL: Documentation, https://github.com/ZechCodes/Bevy/blob/main/bevy/events/README.md
Project-URL: Repository, https://github.com/ZechCodes/Bevy/tree/main/bevy/events
